{
  "Settings": {
    "ServerName": "Bunker Alpha",
    "Port": 8080,
    "RequirePassword": true,
    "ServerPassword": "alpha_pass",
    "AdminEmail": ""
  },
  "Channels": [
    { "Id": "hdr_a_ops",  "Name": "Operations", "Type": "Header" },
    { "Id": "a_cmd_v",    "Name": "Command",     "Type": "Voice"  },
    { "Id": "a_sit_v",    "Name": "Situational", "Type": "Voice"  },
    { "Id": "a_ops_t",    "Name": "ops-log",     "Type": "Text"   },
    { "Id": "hdr_a_soc",  "Name": "Social",      "Type": "Header" },
    { "Id": "a_hang_v",   "Name": "Hangout",     "Type": "Voice"  },
    { "Id": "a_gen_t",    "Name": "general",     "Type": "Text"   }
  ]
}
